lib_video_parser/__init__.py
lib_video_parser/parser.py
lib_video_parser-1.1.dist-info/METADATA
lib_video_parser-1.1.dist-info/WHEEL
lib_video_parser-1.1.dist-info/top_level.txt
lib_video_parser-1.1.dist-info/RECORD
