Metadata-Version: 2.4
Name: lib_video_parser
Version: 1.1
Summary: Library for parse video files
Home-page: https://github.com/YuranIgnatenko/lib_video_parser
Author: Yurij
Author-email: yuran.ignatenko@yandex.ru
Requires-Dist: requests
Requires-Dist: beautifulsoup4
Requires-Dist: fake_useragent
Requires-Dist: aiohttp
Dynamic: author
Dynamic: author-email
Dynamic: description
Dynamic: description-content-type
Dynamic: home-page
Dynamic: requires-dist
Dynamic: summary
